mfcn/__init__.py
mfcn/mkn_globals.py
mfcn/mkn_utils.py
mfcn/solutions.py
MKN_third_codes-0.6.6.3.dist-info/LICENSE.txt
MKN_third_codes-0.6.6.3.dist-info/METADATA
MKN_third_codes-0.6.6.3.dist-info/WHEEL
MKN_third_codes-0.6.6.3.dist-info/top_level.txt
MKN_third_codes-0.6.6.3.dist-info/RECORD
