Metadata-Version: 2.1
Name: MKN-third-codes
Version: 0.6.6.3
Summary: Python library with standart solutions for probability tasks
Author: Dolgun Ivan
Author-email: vanadolgun@gmail.com
License: MIT
License-File: LICENSE.txt
